tests/test_typedlist.py
tests/test_typedlist_edge_cases.py
typedcollections/__init__.py
typedcollections/exceptions.py
typedcollections/typedlist.py
typedcollections-0.1.0.dist-info/METADATA
typedcollections-0.1.0.dist-info/WHEEL
typedcollections-0.1.0.dist-info/top_level.txt
typedcollections-0.1.0.dist-info/RECORD
